<?xml version="1.0" encoding="UTF-8"?><TED_EXPORT xmlns="http://publications.europa.eu/TED_schema/Export" xmlns:xsi="http://www.w3.org/2001/XMLSchema-instance" xmlns:xlink="http://www.w3.org/1999/xlink" xsi:schemaLocation="http://publications.europa.eu/TED_schema/Export TED_EXPORT.xsd" DOC_ID="023855-2011" EDITION="2011016"><TECHNICAL_SECTION><RECEPTION_ID>11-017709-016</RECEPTION_ID><DELETION_DATE>20110501</DELETION_DATE><FORM_LG_LIST>FR </FORM_LG_LIST><COMMENTS>From Convertor</COMMENTS><OLD_HEADING>2180</OLD_HEADING></TECHNICAL_SECTION><LINKS_SECTION><XML_SCHEMA_DEFINITION_LINK xlink:title="TED WEBSITE" xlink:href="http://ted.europa.eu" xlink:type="simple"></XML_SCHEMA_DEFINITION_LINK><OFFICIAL_FORMS_LINK xlink:href="http://ted.europa.eu" xlink:type="simple"></OFFICIAL_FORMS_LINK><FORMS_LABELS_LINK xlink:href="http://ted.europa.eu" xlink:type="simple"></FORMS_LABELS_LINK><ORIGINAL_CPV_LINK xlink:href="http://ted.europa.eu" xlink:type="simple "></ORIGINAL_CPV_LINK><ORIGINAL_NUTS_LINK xlink:href="http://ted.europa.eu" xlink:type="simple"></ORIGINAL_NUTS_LINK></LINKS_SECTION><CODED_DATA_SECTION><REF_OJS><COLL_OJ>S</COLL_OJ><NO_OJ>16</NO_OJ><DATE_PUB>20110125</DATE_PUB></REF_OJS><NOTICE_DATA><NO_DOC_OJS>2011/S 16-023855</NO_DOC_OJS><URI_LIST><URI_DOC LG="FR">http://ted.europa.eu/udl?uri=TED:NOTICE:023855-2011:TEXT:FR:HTML</URI_DOC></URI_LIST><LG_ORIG>FR</LG_ORIG><ISO_COUNTRY VALUE="FR"></ISO_COUNTRY><IA_URL_GENERAL></IA_URL_GENERAL><ORIGINAL_CPV CODE="33124130">diagnostic supplies</ORIGINAL_CPV><ORIGINAL_NUTS CODE="FR716">Rhône</ORIGINAL_NUTS><VALUES_LIST></VALUES_LIST><REF_NOTICE><NO_DOC_OJS>2010/S 63-093896</NO_DOC_OJS></REF_NOTICE></NOTICE_DATA><CODIF_DATA><DS_DATE_DISPATCH>20110121</DS_DATE_DISPATCH><AA_AUTHORITY_TYPE CODE="8">Other</AA_AUTHORITY_TYPE><TD_DOCUMENT_TYPE CODE="7">Contract award</TD_DOCUMENT_TYPE><NC_CONTRACT_NATURE CODE="2">Supply contract</NC_CONTRACT_NATURE><PR_PROC CODE="4">Negotiated procedure</PR_PROC><RP_REGULATION CODE="5">European Union, with participation by GPA countries</RP_REGULATION><TY_TYPE_BID CODE="9">Not applicable</TY_TYPE_BID><AC_AWARD_CRIT CODE="2">The most economic tender</AC_AWARD_CRIT><MA_MAIN_ACTIVITIES CODE="H">Health</MA_MAIN_ACTIVITIES><HEADING>01237</HEADING></CODIF_DATA></CODED_DATA_SECTION><TRANSLATION_SECTION><ML_TITLES><ML_TI_DOC LG="BG"><TI_CY>F</TI_CY><TI_TOWN>Лион</TI_TOWN><TI_TEXT>Принадлежности за диагностика</TI_TEXT></ML_TI_DOC><ML_TI_DOC LG="CS"><TI_CY>F</TI_CY><TI_TOWN>Lyon</TI_TOWN><TI_TEXT>Diagnostické doplňky</TI_TEXT></ML_TI_DOC><ML_TI_DOC LG="DA"><TI_CY>F</TI_CY><TI_TOWN>Lyon</TI_TOWN><TI_TEXT>Diagnostiske artikler</TI_TEXT></ML_TI_DOC><ML_TI_DOC LG="DE"><TI_CY>F</TI_CY><TI_TOWN>Lyon</TI_TOWN><TI_TEXT>Diagnostische Ausstattung</TI_TEXT></ML_TI_DOC><ML_TI_DOC LG="ET"><TI_CY>F</TI_CY><TI_TOWN>Lyon</TI_TOWN><TI_TEXT>Diagnostikatarvikud</TI_TEXT></ML_TI_DOC><ML_TI_DOC LG="EL"><TI_CY>F</TI_CY><TI_TOWN>Λυών</TI_TOWN><TI_TEXT>Προμήθειες συσκευών διαγνωστικής</TI_TEXT></ML_TI_DOC><ML_TI_DOC LG="EN"><TI_CY>F</TI_CY><TI_TOWN>Lyon</TI_TOWN><TI_TEXT>diagnostic supplies</TI_TEXT></ML_TI_DOC><ML_TI_DOC LG="ES"><TI_CY>F</TI_CY><TI_TOWN>Lyón</TI_TOWN><TI_TEXT>Material para diagnóstico</TI_TEXT></ML_TI_DOC><ML_TI_DOC LG="FR"><TI_CY>F</TI_CY><TI_TOWN>Lyon</TI_TOWN><TI_TEXT>Fournitures pour diagnostic</TI_TEXT></ML_TI_DOC><ML_TI_DOC LG="IT"><TI_CY>F</TI_CY><TI_TOWN>Lione</TI_TOWN><TI_TEXT>Presidi diagnostici</TI_TEXT></ML_TI_DOC><ML_TI_DOC LG="LV"><TI_CY>F</TI_CY><TI_TOWN>Liona</TI_TOWN><TI_TEXT>Diagnostikas piederumi</TI_TEXT></ML_TI_DOC><ML_TI_DOC LG="LT"><TI_CY>F</TI_CY><TI_TOWN>Lijonas</TI_TOWN><TI_TEXT>Diagnostikos medžiagos</TI_TEXT></ML_TI_DOC><ML_TI_DOC LG="GA"><TI_CY>F</TI_CY><TI_TOWN>Lyon</TI_TOWN><TI_TEXT>Diagnostic supplies</TI_TEXT></ML_TI_DOC><ML_TI_DOC LG="HU"><TI_CY>F</TI_CY><TI_TOWN>Lyon</TI_TOWN><TI_TEXT>Diagnosztikai kellékek</TI_TEXT></ML_TI_DOC><ML_TI_DOC LG="MT"><TI_CY>F</TI_CY><TI_TOWN>Lyons</TI_TOWN><TI_TEXT>Fornimenti tad-dianjożi</TI_TEXT></ML_TI_DOC><ML_TI_DOC LG="NL"><TI_CY>F</TI_CY><TI_TOWN>Lyon</TI_TOWN><TI_TEXT>Diagnostische benodigdheden</TI_TEXT></ML_TI_DOC><ML_TI_DOC LG="PL"><TI_CY>F</TI_CY><TI_TOWN>Lyon</TI_TOWN><TI_TEXT>Wyroby diagnostyczne</TI_TEXT></ML_TI_DOC><ML_TI_DOC LG="PT"><TI_CY>F</TI_CY><TI_TOWN>Lião</TI_TOWN><TI_TEXT>Material para diagnóstico</TI_TEXT></ML_TI_DOC><ML_TI_DOC LG="RO"><TI_CY>F</TI_CY><TI_TOWN>Lyon</TI_TOWN><TI_TEXT>Accesorii de diagnosticare</TI_TEXT></ML_TI_DOC><ML_TI_DOC LG="SK"><TI_CY>F</TI_CY><TI_TOWN>Lyon</TI_TOWN><TI_TEXT>Diagnostický spotrebný materiál</TI_TEXT></ML_TI_DOC><ML_TI_DOC LG="SL"><TI_CY>F</TI_CY><TI_TOWN>Lyon</TI_TOWN><TI_TEXT>Potrebščine za diagnostiko</TI_TEXT></ML_TI_DOC><ML_TI_DOC LG="FI"><TI_CY>F</TI_CY><TI_TOWN>Lyon</TI_TOWN><TI_TEXT>Diagnostiikkatarvikkeet</TI_TEXT></ML_TI_DOC><ML_TI_DOC LG="SV"><TI_CY>F</TI_CY><TI_TOWN>Lyon</TI_TOWN><TI_TEXT>Diagnostiska artiklar</TI_TEXT></ML_TI_DOC></ML_TITLES><ML_AA_NAMES><AA_NAME LG="FR">Hospices civils de Lyon</AA_NAME></ML_AA_NAMES></TRANSLATION_SECTION><FORM_SECTION><CONTRACT_AWARD CATEGORY="ORIGINAL" LG="FR" VERSION="R2.0.7.S03.E01" FORM="3"><FD_CONTRACT_AWARD CTYPE="SUPPLIES"><CONTACTING_AUTHORITY_INFORMATION><NAME_ADDRESSES_CONTACT_CONTRACT_AWARD><CA_CE_CONCESSIONAIRE_PROFILE><ORGANISATION>Hospices civils de Lyon</ORGANISATION><ADDRESS>45 rue Villon</ADDRESS><TOWN>Lyon Cedex 08</TOWN><POSTAL_CODE>69373</POSTAL_CODE><COUNTRY VALUE="FR"></COUNTRY><ATTENTION>M. Moinard Daniel</ATTENTION></CA_CE_CONCESSIONAIRE_PROFILE></NAME_ADDRESSES_CONTACT_CONTRACT_AWARD><TYPE_AND_ACTIVITIES_AND_PURCHASING_ON_BEHALF><TYPE_AND_ACTIVITIES><TYPE_OF_CONTRACTING_AUTHORITY_OTHER VALUE="OTHER"></TYPE_OF_CONTRACTING_AUTHORITY_OTHER><TYPE_OF_ACTIVITY VALUE="HEALTH"></TYPE_OF_ACTIVITY></TYPE_AND_ACTIVITIES><PURCHASING_ON_BEHALF VALUE="NO"></PURCHASING_ON_BEHALF></TYPE_AND_ACTIVITIES_AND_PURCHASING_ON_BEHALF></CONTACTING_AUTHORITY_INFORMATION><OBJECT_CONTRACT_INFORMATION_CONTRACT_AWARD_NOTICE><DESCRIPTION_AWARD_NOTICE_INFORMATION><TITLE_CONTRACT><P>E11_0605b.</P></TITLE_CONTRACT><TYPE_CONTRACT_LOCATION_W_PUB><TYPE_CONTRACT VALUE="SUPPLIES"></TYPE_CONTRACT><TYPE_SUPPLIES_CONTRACT VALUE="PURCHASE"></TYPE_SUPPLIES_CONTRACT></TYPE_CONTRACT_LOCATION_W_PUB><LOCATION_NUTS><LOCATION><P>agglomération lyonnaise.</P></LOCATION><NUTS CODE="FR716"></NUTS></LOCATION_NUTS><NOTICE_INVOLVES_DESC VALUE="CONCLUSION_FRAMEWORK_AGREEMENT"></NOTICE_INVOLVES_DESC><SHORT_CONTRACT_DESCRIPTION><P>Réactifs pour virologie parasitologie mycologie et bactériologie.</P></SHORT_CONTRACT_DESCRIPTION><CPV><CPV_MAIN><CPV_CODE CODE="33124130"></CPV_CODE></CPV_MAIN></CPV><CONTRACT_COVERED_GPA VALUE="YES"></CONTRACT_COVERED_GPA></DESCRIPTION_AWARD_NOTICE_INFORMATION></OBJECT_CONTRACT_INFORMATION_CONTRACT_AWARD_NOTICE><PROCEDURE_DEFINITION_CONTRACT_AWARD_NOTICE><TYPE_OF_PROCEDURE_DEF><PT_NEGOTIATED_WITH_COMPETITION></PT_NEGOTIATED_WITH_COMPETITION></TYPE_OF_PROCEDURE_DEF><AWARD_CRITERIA_CONTRACT_AWARD_NOTICE_INFORMATION><AWARD_CRITERIA_DETAIL_F03><MOST_ECONOMICALLY_ADVANTAGEOUS_TENDER_SHORT><CRITERIA_DEFINITION><ORDER_C>1</ORDER_C><CRITERIA>Qualité analytique</CRITERIA><WEIGHTING>60</WEIGHTING></CRITERIA_DEFINITION><CRITERIA_DEFINITION><ORDER_C>2</ORDER_C><CRITERIA>Coût d'utilisation</CRITERIA><WEIGHTING>40</WEIGHTING></CRITERIA_DEFINITION></MOST_ECONOMICALLY_ADVANTAGEOUS_TENDER_SHORT></AWARD_CRITERIA_DETAIL_F03><F03_IS_ELECTRONIC_AUCTION_USABLE VALUE="NO"></F03_IS_ELECTRONIC_AUCTION_USABLE></AWARD_CRITERIA_CONTRACT_AWARD_NOTICE_INFORMATION><ADMINISTRATIVE_INFORMATION_CONTRACT_AWARD><FILE_REFERENCE_NUMBER><P>E11_0605B</P></FILE_REFERENCE_NUMBER><PREVIOUS_PUBLICATION_INFORMATION_NOTICE_F3><PREVIOUS_PUBLICATION_EXISTS_F3><CNT_NOTICE_INFORMATION><CNT_NOTICE_INFORMATION_S CHOICE="CONTRACT_NOTICE"></CNT_NOTICE_INFORMATION_S><NOTICE_NUMBER_OJ>2010/S 063-093896</NOTICE_NUMBER_OJ><DATE_OJ><DAY>31</DAY><MONTH>03</MONTH><YEAR>2010</YEAR></DATE_OJ></CNT_NOTICE_INFORMATION></PREVIOUS_PUBLICATION_EXISTS_F3></PREVIOUS_PUBLICATION_INFORMATION_NOTICE_F3></ADMINISTRATIVE_INFORMATION_CONTRACT_AWARD></PROCEDURE_DEFINITION_CONTRACT_AWARD_NOTICE><AWARD_OF_CONTRACT><CONTRACT_NUMBER>20111044</CONTRACT_NUMBER><LOT_NUMBER>98</LOT_NUMBER><CONTRACT_TITLE><P>Quantification de l'ADN du CMV et de l'EBV (BIO. MOL).</P></CONTRACT_TITLE><CONTRACT_AWARD_DATE><DAY>27</DAY><MONTH>12</MONTH><YEAR>2010</YEAR></CONTRACT_AWARD_DATE><OFFERS_RECEIVED_NUMBER>6</OFFERS_RECEIVED_NUMBER><ECONOMIC_OPERATOR_NAME_ADDRESS><CONTACT_DATA_WITHOUT_RESPONSIBLE_NAME><ORGANISATION>Argène</ORGANISATION><ADDRESS>Parc technologique Delta Sud</ADDRESS><TOWN>Verniolle</TOWN><POSTAL_CODE>09340</POSTAL_CODE><COUNTRY VALUE="FR"></COUNTRY></CONTACT_DATA_WITHOUT_RESPONSIBLE_NAME></ECONOMIC_OPERATOR_NAME_ADDRESS><CONTRACT_VALUE_INFORMATION><INITIAL_ESTIMATED_TOTAL_VALUE_CONTRACT CURRENCY="EUR"><VALUE_COST FMTVAL="104515.05">104 515,05</VALUE_COST></INITIAL_ESTIMATED_TOTAL_VALUE_CONTRACT><MORE_INFORMATION_IF_ANNUAL_MONTHLY><NUMBER_OF_YEARS>3</NUMBER_OF_YEARS></MORE_INFORMATION_IF_ANNUAL_MONTHLY></CONTRACT_VALUE_INFORMATION><MORE_INFORMATION_TO_SUB_CONTRACTED><NO_CONTRACT_LIKELY_SUB_CONTRACTED></NO_CONTRACT_LIKELY_SUB_CONTRACTED></MORE_INFORMATION_TO_SUB_CONTRACTED></AWARD_OF_CONTRACT><COMPLEMENTARY_INFORMATION_CONTRACT_AWARD><RELATES_TO_EU_PROJECT_NO></RELATES_TO_EU_PROJECT_NO><ADDITIONAL_INFORMATION><P>Annonce no374, BOAMP 064 B du 1.4.2010.</P><P>Date d'envoi du présent avis au JOUE et au BOAMP: 21.1.2011.</P></ADDITIONAL_INFORMATION><PROCEDURES_FOR_APPEAL><APPEAL_PROCEDURE_BODY_RESPONSIBLE><CONTACT_DATA_WITHOUT_RESPONSIBLE_NAME><ORGANISATION>Tribunal administratif de Lyon</ORGANISATION><ADDRESS>184 rue Duguesclin</ADDRESS><TOWN>Lyon</TOWN><POSTAL_CODE>69003</POSTAL_CODE><COUNTRY VALUE="FR"></COUNTRY><E_MAIL>greffe.ta-lyon@juradm.fr</E_MAIL><PHONE>+33 478141010</PHONE><FAX>+33 478141065</FAX></CONTACT_DATA_WITHOUT_RESPONSIBLE_NAME></APPEAL_PROCEDURE_BODY_RESPONSIBLE><LODGING_OF_APPEALS><LODGING_OF_APPEALS_PRECISION><P>Possibilité de former un référé précontractuel avant la signature du marché (article L551-1 du code de justice administrative) et un référé contractuel en sus des autres voies de recours.</P></LODGING_OF_APPEALS_PRECISION></LODGING_OF_APPEALS></PROCEDURES_FOR_APPEAL><NOTICE_DISPATCH_DATE><DAY>21</DAY><MONTH>01</MONTH><YEAR>2011</YEAR></NOTICE_DISPATCH_DATE></COMPLEMENTARY_INFORMATION_CONTRACT_AWARD></FD_CONTRACT_AWARD></CONTRACT_AWARD></FORM_SECTION></TED_EXPORT>