<?xml version="1.0" encoding="UTF-8"?><TED_EXPORT xmlns="http://publications.europa.eu/TED_schema/Export" xmlns:xsi="http://www.w3.org/2001/XMLSchema-instance" xmlns:xlink="http://www.w3.org/1999/xlink" xsi:schemaLocation="http://publications.europa.eu/TED_schema/Export TED_EXPORT.xsd" DOC_ID="024248-2011" EDITION="2011016"><TECHNICAL_SECTION><RECEPTION_ID>11-017903-014</RECEPTION_ID><DELETION_DATE>20110501</DELETION_DATE><FORM_LG_LIST>FR </FORM_LG_LIST><COMMENTS>From Convertor</COMMENTS><OLD_HEADING>2280</OLD_HEADING></TECHNICAL_SECTION><LINKS_SECTION><XML_SCHEMA_DEFINITION_LINK xlink:title="TED WEBSITE" xlink:href="http://ted.europa.eu" xlink:type="simple"></XML_SCHEMA_DEFINITION_LINK><OFFICIAL_FORMS_LINK xlink:href="http://ted.europa.eu" xlink:type="simple"></OFFICIAL_FORMS_LINK><FORMS_LABELS_LINK xlink:href="http://ted.europa.eu" xlink:type="simple"></FORMS_LABELS_LINK><ORIGINAL_CPV_LINK xlink:href="http://ted.europa.eu" xlink:type="simple "></ORIGINAL_CPV_LINK><ORIGINAL_NUTS_LINK xlink:href="http://ted.europa.eu" xlink:type="simple"></ORIGINAL_NUTS_LINK></LINKS_SECTION><CODED_DATA_SECTION><REF_OJS><COLL_OJ>S</COLL_OJ><NO_OJ>16</NO_OJ><DATE_PUB>20110125</DATE_PUB></REF_OJS><NOTICE_DATA><NO_DOC_OJS>2011/S 16-024248</NO_DOC_OJS><URI_LIST><URI_DOC LG="FR">http://ted.europa.eu/udl?uri=TED:NOTICE:024248-2011:TEXT:FR:HTML</URI_DOC></URI_LIST><LG_ORIG>FR</LG_ORIG><ISO_COUNTRY VALUE="FR"></ISO_COUNTRY><IA_URL_GENERAL>http://www.sdis26.fr</IA_URL_GENERAL><ORIGINAL_CPV CODE="35111100">breathing apparatus for firefighting</ORIGINAL_CPV><ORIGINAL_NUTS CODE="FR713">Drôme</ORIGINAL_NUTS><VALUES_LIST><VALUES TYPE="GLOBAL"><RANGE_VALUE><VALUE CURRENCY="EUR">30 000,00</VALUE><VALUE CURRENCY="EUR">150 000,00</VALUE></RANGE_VALUE></VALUES></VALUES_LIST><REF_NOTICE><NO_DOC_OJS>2010/S 103-156799</NO_DOC_OJS></REF_NOTICE></NOTICE_DATA><CODIF_DATA><DS_DATE_DISPATCH>20110121</DS_DATE_DISPATCH><AA_AUTHORITY_TYPE CODE="6">Body governed by public law</AA_AUTHORITY_TYPE><TD_DOCUMENT_TYPE CODE="7">Contract award</TD_DOCUMENT_TYPE><NC_CONTRACT_NATURE CODE="4">Service contract</NC_CONTRACT_NATURE><PR_PROC CODE="1">Open procedure</PR_PROC><RP_REGULATION CODE="4">European Union</RP_REGULATION><TY_TYPE_BID CODE="9">Not applicable</TY_TYPE_BID><AC_AWARD_CRIT CODE="2">The most economic tender</AC_AWARD_CRIT><MA_MAIN_ACTIVITIES CODE="O">Other</MA_MAIN_ACTIVITIES><HEADING>01337</HEADING></CODIF_DATA></CODED_DATA_SECTION><TRANSLATION_SECTION><ML_TITLES><ML_TI_DOC LG="BG"><TI_CY>F</TI_CY><TI_TOWN>Valence</TI_TOWN><TI_TEXT>Бутилки за дихателни апарати за борба с пожарите</TI_TEXT></ML_TI_DOC><ML_TI_DOC LG="CS"><TI_CY>F</TI_CY><TI_TOWN>Valence</TI_TOWN><TI_TEXT>Dýchací přístroje pro požárníky</TI_TEXT></ML_TI_DOC><ML_TI_DOC LG="DA"><TI_CY>F</TI_CY><TI_TOWN>Valence</TI_TOWN><TI_TEXT>Indåndingsapparater til brandbekæmpelse</TI_TEXT></ML_TI_DOC><ML_TI_DOC LG="DE"><TI_CY>F</TI_CY><TI_TOWN>Valence</TI_TOWN><TI_TEXT>Atemschutzgeräte für die Brandbekämpfung</TI_TEXT></ML_TI_DOC><ML_TI_DOC LG="ET"><TI_CY>F</TI_CY><TI_TOWN>Valence</TI_TOWN><TI_TEXT>Hingamisaparaadid tuletõrjujatele</TI_TEXT></ML_TI_DOC><ML_TI_DOC LG="EL"><TI_CY>F</TI_CY><TI_TOWN>Valence</TI_TOWN><TI_TEXT>Αναπνευστικές συσκευές πυρόσβεσης</TI_TEXT></ML_TI_DOC><ML_TI_DOC LG="EN"><TI_CY>F</TI_CY><TI_TOWN>Valence</TI_TOWN><TI_TEXT>breathing apparatus for firefighting</TI_TEXT></ML_TI_DOC><ML_TI_DOC LG="ES"><TI_CY>F</TI_CY><TI_TOWN>Valence</TI_TOWN><TI_TEXT>Aparatos respiratorios para extinción de incendios</TI_TEXT></ML_TI_DOC><ML_TI_DOC LG="FR"><TI_CY>F</TI_CY><TI_TOWN>Valence</TI_TOWN><TI_TEXT>Appareils respiratoires pour la lutte contre l'incendie</TI_TEXT></ML_TI_DOC><ML_TI_DOC LG="IT"><TI_CY>F</TI_CY><TI_TOWN>Valence</TI_TOWN><TI_TEXT>Apparecchi respiratori antincendio</TI_TEXT></ML_TI_DOC><ML_TI_DOC LG="LV"><TI_CY>F</TI_CY><TI_TOWN>Valence</TI_TOWN><TI_TEXT>Ugunsdzēsēju elpošanas aparāti</TI_TEXT></ML_TI_DOC><ML_TI_DOC LG="LT"><TI_CY>F</TI_CY><TI_TOWN>Valence</TI_TOWN><TI_TEXT>Kvėpavimo aparatai, naudojami gesinant gaisrus</TI_TEXT></ML_TI_DOC><ML_TI_DOC LG="GA"><TI_CY>F</TI_CY><TI_TOWN>Valence</TI_TOWN><TI_TEXT>Breathing apparatus for firefighting</TI_TEXT></ML_TI_DOC><ML_TI_DOC LG="HU"><TI_CY>F</TI_CY><TI_TOWN>Valence</TI_TOWN><TI_TEXT>Légzőkészülék tűzoltók számára</TI_TEXT></ML_TI_DOC><ML_TI_DOC LG="MT"><TI_CY>F</TI_CY><TI_TOWN>Valence</TI_TOWN><TI_TEXT>Apparat tan-nifs għall-użu fit-tifi tan-nar</TI_TEXT></ML_TI_DOC><ML_TI_DOC LG="NL"><TI_CY>F</TI_CY><TI_TOWN>Valence</TI_TOWN><TI_TEXT>Ademhalingsapparatuur voor brandbestrijding</TI_TEXT></ML_TI_DOC><ML_TI_DOC LG="PL"><TI_CY>F</TI_CY><TI_TOWN>Valence</TI_TOWN><TI_TEXT>Respiratory strażackie</TI_TEXT></ML_TI_DOC><ML_TI_DOC LG="PT"><TI_CY>F</TI_CY><TI_TOWN>Valence</TI_TOWN><TI_TEXT>Aparelhos respiratórios para combate a incêndios</TI_TEXT></ML_TI_DOC><ML_TI_DOC LG="RO"><TI_CY>F</TI_CY><TI_TOWN>Valence</TI_TOWN><TI_TEXT>Aparate de respirat pentru intervenţiile în caz de incendiu</TI_TEXT></ML_TI_DOC><ML_TI_DOC LG="SK"><TI_CY>F</TI_CY><TI_TOWN>Valence</TI_TOWN><TI_TEXT>Dýchacie prístroje pre požiarnikov</TI_TEXT></ML_TI_DOC><ML_TI_DOC LG="SL"><TI_CY>F</TI_CY><TI_TOWN>Valence</TI_TOWN><TI_TEXT>Dihalni aparati za gašenje požara</TI_TEXT></ML_TI_DOC><ML_TI_DOC LG="FI"><TI_CY>F</TI_CY><TI_TOWN>Valence</TI_TOWN><TI_TEXT>Palomiesten hengityslaitteet</TI_TEXT></ML_TI_DOC><ML_TI_DOC LG="SV"><TI_CY>F</TI_CY><TI_TOWN>Valence</TI_TOWN><TI_TEXT>Andningsapparater för brandsläckning</TI_TEXT></ML_TI_DOC></ML_TITLES><ML_AA_NAMES><AA_NAME LG="FR">SDIS26</AA_NAME></ML_AA_NAMES></TRANSLATION_SECTION><FORM_SECTION><CONTRACT_AWARD CATEGORY="ORIGINAL" LG="FR" VERSION="R2.0.7.S03.E01" FORM="3"><FD_CONTRACT_AWARD CTYPE="SERVICES"><CONTACTING_AUTHORITY_INFORMATION><NAME_ADDRESSES_CONTACT_CONTRACT_AWARD><CA_CE_CONCESSIONAIRE_PROFILE><ORGANISATION>SDIS26</ORGANISATION><ADDRESS>235 route de Montélier, BP 147, Cedex 9</ADDRESS><TOWN>Valence</TOWN><POSTAL_CODE>26905</POSTAL_CODE><COUNTRY VALUE="FR"></COUNTRY><ATTENTION>le président du conseil d'administration</ATTENTION><PHONE>+33 475827200</PHONE><E_MAIL>marchespublics@sdis26.fr</E_MAIL><FAX>+33 475827351</FAX></CA_CE_CONCESSIONAIRE_PROFILE><INTERNET_ADDRESSES_CONTRACT_AWARD><URL_GENERAL>http://www.sdis26.fr</URL_GENERAL></INTERNET_ADDRESSES_CONTRACT_AWARD></NAME_ADDRESSES_CONTACT_CONTRACT_AWARD><TYPE_AND_ACTIVITIES_AND_PURCHASING_ON_BEHALF><TYPE_AND_ACTIVITIES><TYPE_OF_CONTRACTING_AUTHORITY VALUE="BODY_PUBLIC"></TYPE_OF_CONTRACTING_AUTHORITY><TYPE_OF_ACTIVITY_OTHER VALUE="OTHER">service d'incendie et de Secours</TYPE_OF_ACTIVITY_OTHER></TYPE_AND_ACTIVITIES><PURCHASING_ON_BEHALF VALUE="NO"></PURCHASING_ON_BEHALF></TYPE_AND_ACTIVITIES_AND_PURCHASING_ON_BEHALF></CONTACTING_AUTHORITY_INFORMATION><OBJECT_CONTRACT_INFORMATION_CONTRACT_AWARD_NOTICE><DESCRIPTION_AWARD_NOTICE_INFORMATION><TYPE_CONTRACT_LOCATION_W_PUB><TYPE_CONTRACT VALUE="SERVICES"></TYPE_CONTRACT><SERVICE_CATEGORY_PUB>1</SERVICE_CATEGORY_PUB></TYPE_CONTRACT_LOCATION_W_PUB><LOCATION_NUTS><LOCATION><P>Département de la Drôme.</P></LOCATION><NUTS CODE="FR713"></NUTS></LOCATION_NUTS><SHORT_CONTRACT_DESCRIPTION><P>Vérification et requalification des récipients sous pression affaire no10/11aoo. Marché à bons de commande unique avec mini et maxi et un opérateur économique.</P></SHORT_CONTRACT_DESCRIPTION><CPV><CPV_MAIN><CPV_CODE CODE="35111100"></CPV_CODE></CPV_MAIN></CPV><CONTRACT_COVERED_GPA VALUE="NO"></CONTRACT_COVERED_GPA></DESCRIPTION_AWARD_NOTICE_INFORMATION><TOTAL_FINAL_VALUE><COSTS_RANGE_AND_CURRENCY_WITH_VAT_RATE CURRENCY="EUR"><RANGE_VALUE_COST><LOW_VALUE FMTVAL="30000.00">30 000,00</LOW_VALUE><HIGH_VALUE FMTVAL="150000.00">150 000,00</HIGH_VALUE></RANGE_VALUE_COST><EXCLUDING_VAT></EXCLUDING_VAT></COSTS_RANGE_AND_CURRENCY_WITH_VAT_RATE></TOTAL_FINAL_VALUE></OBJECT_CONTRACT_INFORMATION_CONTRACT_AWARD_NOTICE><PROCEDURE_DEFINITION_CONTRACT_AWARD_NOTICE><TYPE_OF_PROCEDURE_DEF><PT_OPEN></PT_OPEN></TYPE_OF_PROCEDURE_DEF><AWARD_CRITERIA_CONTRACT_AWARD_NOTICE_INFORMATION><AWARD_CRITERIA_DETAIL_F03><MOST_ECONOMICALLY_ADVANTAGEOUS_TENDER_SHORT><CRITERIA_DEFINITION><ORDER_C>1</ORDER_C><CRITERIA>Prix des prestations</CRITERIA><WEIGHTING>50</WEIGHTING></CRITERIA_DEFINITION><CRITERIA_DEFINITION><ORDER_C>2</ORDER_C><CRITERIA>Valeur technique</CRITERIA><WEIGHTING>40</WEIGHTING></CRITERIA_DEFINITION><CRITERIA_DEFINITION><ORDER_C>3</ORDER_C><CRITERIA>Durée d'immobilisation des bouteilles</CRITERIA><WEIGHTING>10</WEIGHTING></CRITERIA_DEFINITION></MOST_ECONOMICALLY_ADVANTAGEOUS_TENDER_SHORT></AWARD_CRITERIA_DETAIL_F03><F03_IS_ELECTRONIC_AUCTION_USABLE VALUE="NO"></F03_IS_ELECTRONIC_AUCTION_USABLE></AWARD_CRITERIA_CONTRACT_AWARD_NOTICE_INFORMATION><ADMINISTRATIVE_INFORMATION_CONTRACT_AWARD><FILE_REFERENCE_NUMBER><P>1011AOO</P></FILE_REFERENCE_NUMBER><PREVIOUS_PUBLICATION_INFORMATION_NOTICE_F3><PREVIOUS_PUBLICATION_EXISTS_F3><CNT_NOTICE_INFORMATION><CNT_NOTICE_INFORMATION_S CHOICE="CONTRACT_NOTICE"></CNT_NOTICE_INFORMATION_S><NOTICE_NUMBER_OJ>2010/S 103-156799</NOTICE_NUMBER_OJ><DATE_OJ><DAY>29</DAY><MONTH>05</MONTH><YEAR>2010</YEAR></DATE_OJ></CNT_NOTICE_INFORMATION></PREVIOUS_PUBLICATION_EXISTS_F3></PREVIOUS_PUBLICATION_INFORMATION_NOTICE_F3></ADMINISTRATIVE_INFORMATION_CONTRACT_AWARD></PROCEDURE_DEFINITION_CONTRACT_AWARD_NOTICE><AWARD_OF_CONTRACT><CONTRACT_TITLE><P>Marché: 2010/078. Attribué.</P></CONTRACT_TITLE><CONTRACT_AWARD_DATE><DAY>21</DAY><MONTH>07</MONTH><YEAR>2010</YEAR></CONTRACT_AWARD_DATE><OFFERS_RECEIVED_NUMBER>2</OFFERS_RECEIVED_NUMBER><ECONOMIC_OPERATOR_NAME_ADDRESS><CONTACT_DATA_WITHOUT_RESPONSIBLE_NAME><ORGANISATION>BCH Compresseurs</ORGANISATION><ADDRESS>105 impasse Lavoisier</ADDRESS><TOWN>Gresy-sur-Aix</TOWN><POSTAL_CODE>73100</POSTAL_CODE><COUNTRY VALUE="FR"></COUNTRY></CONTACT_DATA_WITHOUT_RESPONSIBLE_NAME></ECONOMIC_OPERATOR_NAME_ADDRESS></AWARD_OF_CONTRACT><COMPLEMENTARY_INFORMATION_CONTRACT_AWARD><ADDITIONAL_INFORMATION><P>Annonce n° 161, BOAMP 104 B du 1.6.2010.</P><P>Date d'envoi du présent avis au JOUE et au BOAMP: 21.1.2011.</P></ADDITIONAL_INFORMATION><PROCEDURES_FOR_APPEAL><APPEAL_PROCEDURE_BODY_RESPONSIBLE><CONTACT_DATA_WITHOUT_RESPONSIBLE_NAME><ORGANISATION>Tribunal administratif de Grenoble</ORGANISATION><ADDRESS>place de Verdun</ADDRESS><TOWN>Grenoble</TOWN><POSTAL_CODE>38000</POSTAL_CODE><COUNTRY VALUE="FR"></COUNTRY><PHONE>+33 476429006</PHONE><FAX>+33 476518944</FAX></CONTACT_DATA_WITHOUT_RESPONSIBLE_NAME></APPEAL_PROCEDURE_BODY_RESPONSIBLE><LODGING_INFORMATION_FOR_SERVICE><CONTACT_DATA_WITHOUT_RESPONSIBLE_NAME><ORGANISATION>SDIS26</ORGANISATION><ADDRESS>service marchés publics, 235 route de Montélier, BP 147, Cedex 9</ADDRESS><TOWN>Valence</TOWN><POSTAL_CODE>26905</POSTAL_CODE><COUNTRY VALUE="FR"></COUNTRY><PHONE>+33 475827200</PHONE><FAX>+33 475827351</FAX></CONTACT_DATA_WITHOUT_RESPONSIBLE_NAME></LODGING_INFORMATION_FOR_SERVICE></PROCEDURES_FOR_APPEAL><NOTICE_DISPATCH_DATE><DAY>21</DAY><MONTH>01</MONTH><YEAR>2011</YEAR></NOTICE_DISPATCH_DATE></COMPLEMENTARY_INFORMATION_CONTRACT_AWARD></FD_CONTRACT_AWARD></CONTRACT_AWARD></FORM_SECTION></TED_EXPORT>